---
title: PC Register JVM
tags:
  - JavaSE
related_topics: 
created: 2024-12-26 13:26
modified: 2024-12-27T16:57:52+03:00
questions: 
notes: 
links: 
---

---
[[Вопросы на PC Register JVM]]


---

### PC Register (Program Counter Register) в JVM: что это и зачем нужен?

**PC Register** — э<mark class="hltr-yellow">то один из ключевых компонентов JVM, который используется для управления выполнением байт-кода. Каждый поток в JVM имеет свой собственный PC Register. Это помогает JVM поддерживать многопоточность, поскольку каждый поток может хранить информацию о своём текущем состоянии выполнения.</mark>

#### Основные функции PC Register:

1. **Хранение адреса следующей инструкции**:
    - <mark class="hltr-green2"> В байт-коде JVM инструкции упорядочены последовательно. PC Register указывает на следующую инструкцию, которую нужно выполнить</mark>.
2. **Поддержка многопоточности**:
    - Каждый поток имеет свой независимый PC Register. Это позволяет JVM сохранять состояние выполнения для каждого потока.
3. **Исключение из работы с native методами**:
    - <mark class="hltr-red">Для native методов PC Register не используется, так как их выполнение передаётся платформе.</mark>

---

### Пример использования PC Register:

Представьте, что JVM выполняет следующий код на языке Java:

```java
public class Main {
    public static void main(String[] args) {
        int a = 5;
        int b = 10;
        int sum = a + b;
        System.out.println("Sum: " + sum);
    }
}

```

Когда этот код компилируется, он превращается в байт-код. Например

```java
0: iconst_5
1: istore_1
2: iconst_10
3: istore_2
4: iload_1
5: iload_2
6: iadd
7: istore_3
8: getstatic #2 // Field java/lang/System.out
11: ldc #3      // String Sum: 
13: iload_3
14: invokevirtual #4 // Method java/io/PrintStream.println
17: return

```


#### Как работает PC Register:

1. JVM начинает выполнение с инструкции `0: iconst_5`.
    - PC Register указывает на эту инструкцию.
2. После выполнения `iconst_5`, PC Register обновляется и указывает на следующую инструкцию (`1: istore_1`).
3. Этот процесс продолжается, пока не будет достигнута инструкция `17: return`.

Если поток переключается, JVM сохраняет состояние его PC Register, чтобы можно было вернуться к выполнению с того же места.

---

### Реальный кейс:

#### Задача: Оптимизация многопоточной обработки данных.

В приложении используется пул потоков для обработки пользовательских запросов. Иногда наблюдаются ошибки при выполнении параллельных операций, такие как `ArrayIndexOutOfBoundsException`.

#### Анализ:

1. JVM выполняет код в разных потоках, используя независимые PC Registers.
2. Ошибка может быть вызвана тем, что один из потоков завершает выполнение слишком рано, либо обращается к неправильному индексу массива.

#### Роль PC Register:

Используя профайлер или отладчик (например, VisualVM), можно посмотреть, где находился PC Register в момент сбоя. Это помогает определить, на какой инструкции произошла ошибка и какой поток её вызвал.